{"match":{"name":1,"homeTeam":"Frankreich","guestTeam":"Rumänien","groupName":"A","roundType":1,"cupName":"em 2016","startDate":"1465585200"}}
{"match":{"name":2,"homeTeam":"Albanien","guestTeam":"Schweiz","groupName":"A","roundType":1,"cupName":"em 2016","startDate":"1465650000"}}
{"match":{"name":3,"homeTeam":"Wales","guestTeam":"Slowakei","groupName":"B","roundType":1,"cupName":"em 2016","startDate":"1465660800"}}
{"match":{"name":4,"homeTeam":"England","guestTeam":"Russland","groupName":"B","roundType":1,"cupName":"em 2016","startDate":"1465671600"}}
{"match":{"name":5,"homeTeam":"Türkei","guestTeam":"Kroatien","groupName":"D","roundType":1,"cupName":"em 2016","startDate":"1465736400"}}
{"match":{"name":6,"homeTeam":"Polen","guestTeam":"Nordirland","groupName":"C","roundType":1,"cupName":"em 2016","startDate":"1465747200"}}
{"match":{"name":7,"homeTeam":"Deutschland","guestTeam":"Ukraine","groupName":"C","roundType":1,"cupName":"em 2016","startDate":"1465758000"}}
{"match":{"name":8,"homeTeam":"Spanien","guestTeam":"Tschechien","groupName":"D","roundType":1,"cupName":"em 2016","startDate":"1465822800"}}
{"match":{"name":9,"homeTeam":"Irland","guestTeam":"Schweden","groupName":"E","roundType":1,"cupName":"em 2016","startDate":"1465833600"}}
{"match":{"name":10,"homeTeam":"Belgien","guestTeam":"Italien","groupName":"E","roundType":1,"cupName":"em 2016","startDate":"1465844400"}}
{"match":{"name":11,"homeTeam":"Österreich","guestTeam":"Ungarn","groupName":"F","roundType":1,"cupName":"em 2016","startDate":"1465920000"}}
{"match":{"name":12,"homeTeam":"Portugal","guestTeam":"Island","groupName":"F","roundType":1,"cupName":"em 2016","startDate":"1465930800"}}
{"match":{"name":13,"homeTeam":"Russland","guestTeam":"Slowakei","groupName":"B","roundType":1,"cupName":"em 2016","startDate":"1465995600"}}
{"match":{"name":14,"homeTeam":"Rumänien","guestTeam":"Schweiz","groupName":"A","roundType":1,"cupName":"em 2016","startDate":"1466006400"}}
{"match":{"name":15,"homeTeam":"Frankreich","guestTeam":"Albanien","groupName":"A","roundType":1,"cupName":"em 2016","startDate":"1466017200"}}
{"match":{"name":16,"homeTeam":"England","guestTeam":"Wales","groupName":"B","roundType":1,"cupName":"em 2016","startDate":"1466082000"}}
{"match":{"name":17,"homeTeam":"Ukraine","guestTeam":"Nordirland","groupName":"C","roundType":1,"cupName":"em 2016","startDate":"1466092800"}}
{"match":{"name":18,"homeTeam":"Deutschland","guestTeam":"Polen","groupName":"C","roundType":1,"cupName":"em 2016","startDate":"1466103600"}}
{"match":{"name":19,"homeTeam":"Italien","guestTeam":"Schweden","groupName":"E","roundType":1,"cupName":"em 2016","startDate":"1466168400"}}
{"match":{"name":20,"homeTeam":"Tschechien","guestTeam":"Kroatien","groupName":"D","roundType":1,"cupName":"em 2016","startDate":"1466179200"}}
{"match":{"name":21,"homeTeam":"Spanien","guestTeam":"Türkei","groupName":"D","roundType":1,"cupName":"em 2016","startDate":"1466190000"}}
{"match":{"name":22,"homeTeam":"Belgien","guestTeam":"Irland","groupName":"E","roundType":1,"cupName":"em 2016","startDate":"1466254800"}}
{"match":{"name":23,"homeTeam":"Island","guestTeam":"Ungarn","groupName":"F","roundType":1,"cupName":"em 2016","startDate":"1466265600"}}
{"match":{"name":24,"homeTeam":"Portugal","guestTeam":"Österreich","groupName":"F","roundType":1,"cupName":"em 2016","startDate":"1466276400"}}
{"match":{"name":25,"homeTeam":"Schweiz","guestTeam":"Frankreich","groupName":"A","roundType":1,"cupName":"em 2016","startDate":"1466362800"}}
{"match":{"name":26,"homeTeam":"Rumänien","guestTeam":"Albanien","groupName":"A","roundType":1,"cupName":"em 2016","startDate":"1466362800"}}
{"match":{"name":27,"homeTeam":"Slowakei","guestTeam":"England","groupName":"B","roundType":1,"cupName":"em 2016","startDate":"1466449200"}}
{"match":{"name":28,"homeTeam":"Russland","guestTeam":"Wales","groupName":"B","roundType":1,"cupName":"em 2016","startDate":"1466449200"}}
{"match":{"name":29,"homeTeam":"Ukraine","guestTeam":"Polen","groupName":"C","roundType":1,"cupName":"em 2016","startDate":"1466524800"}}
{"match":{"name":30,"homeTeam":"Nordirland","guestTeam":"Deutschland","groupName":"C","roundType":1,"cupName":"em 2016","startDate":"1466524800"}}
{"match":{"name":31,"homeTeam":"Kroatien","guestTeam":"Spanien","groupName":"D","roundType":1,"cupName":"em 2016","startDate":"1466535600"}}
{"match":{"name":32,"homeTeam":"Tschechien","guestTeam":"Türkei","groupName":"D","roundType":1,"cupName":"em 2016","startDate":"1466535600"}}
{"match":{"name":33,"homeTeam":"Ungarn","guestTeam":"Portugal","groupName":"F","roundType":1,"cupName":"em 2016","startDate":"1466611200"}}
{"match":{"name":34,"homeTeam":"Island","guestTeam":"Österreich","groupName":"F","roundType":1,"cupName":"em 2016","startDate":"1466611200"}}
{"match":{"name":35,"homeTeam":"Italien","guestTeam":"Irland","groupName":"E","roundType":1,"cupName":"em 2016","startDate":"1466622000"}}
{"match":{"name":36,"homeTeam":"Schweden","guestTeam":"Belgien","groupName":"E","roundType":1,"cupName":"em 2016","startDate":"1466622000"}}
